bounded_pool/__init__.py
bounded_pool-0.0.2.dist-info/LICENSE
bounded_pool-0.0.2.dist-info/METADATA
bounded_pool-0.0.2.dist-info/WHEEL
bounded_pool-0.0.2.dist-info/top_level.txt
bounded_pool-0.0.2.dist-info/RECORD
