Metadata-Version: 2.1
Name: bounded-pool
Version: 0.0.2
Summary: Library for running tasks in bounded pool executors.
Home-page: https://github.com/michaelkryukov/bounded_pool
Author: Michael Krukov
Author-email: krukov.michael@ya.ru
Keywords: library
Classifier: Programming Language :: Python :: 3
Classifier: Programming Language :: Python :: 3 :: Only
Classifier: License :: OSI Approved :: MIT License
Classifier: Operating System :: OS Independent
Classifier: Intended Audience :: Developers
Requires-Python: >=3.7
License-File: LICENSE
